ais_database_client/__init__.py
ais_database_client/ais_reader.py
ais_database_client-2025.4.4.dist-info/licenses/LICENSE.txt
ais_database_client-2025.4.4.dist-info/METADATA
ais_database_client-2025.4.4.dist-info/WHEEL
ais_database_client-2025.4.4.dist-info/top_level.txt
ais_database_client-2025.4.4.dist-info/RECORD
