Metadata-Version: 2.4
Name: ais_database_client
Version: 2025.4.4
Summary: Python client to the Space Eye AIS database
Author-email: "Space Eye e.V." <kontakt@space-eye.org>
License: Apache-2.0
Project-URL: Homepage, https://space-eye.info
Project-URL: Bug Tracker, https://gitlab.com/satellitesearch/ais_database_client/-/issues
Project-URL: Source Code, https://gitlab.com/satellitesearch/ais_database_client
Keywords: AIS,SAR
Classifier: Development Status :: 3 - Alpha
Classifier: License :: OSI Approved :: Apache Software License
Classifier: Programming Language :: Python :: 3
Requires-Python: >=3.10
License-File: LICENSE.txt
Requires-Dist: requests
Dynamic: license-file
